.hgignore
CHANGES.txt
LICENSE.txt
MANIFEST.in
README.txt
bootstrap.py
buildout.cfg
setup.py
js/__init__.py
js.namespace.egg-info/PKG-INFO
js.namespace.egg-info/SOURCES.txt
js.namespace.egg-info/dependency_links.txt
js.namespace.egg-info/entry_points.txt
js.namespace.egg-info/namespace_packages.txt
js.namespace.egg-info/not-zip-safe
js.namespace.egg-info/requires.txt
js.namespace.egg-info/top_level.txt
js/namespace/__init__.py
js/namespace/test_namespace.txt
js/namespace/resources/namespace.js