Metadata-Version: 1.0
Name: js.namespace
Version: 0.1
Summary: Fanstatic package providing a small js library for declaring namespaces.
Home-page: UNKNOWN
Author: Daniel Havlik
Author-email: dh@gocept.com
License: BSD
Platform: UNKNOWN
